MANIFEST.in
README.rst
setup.py
ph4_python_whois.egg-info/PKG-INFO
ph4_python_whois.egg-info/SOURCES.txt
ph4_python_whois.egg-info/dependency_links.txt
ph4_python_whois.egg-info/not-zip-safe
ph4_python_whois.egg-info/requires.txt
ph4_python_whois.egg-info/top_level.txt
ph4whois/__init__.py
ph4whois/parser.py
ph4whois/time_zones.py
ph4whois/whois.py
ph4whois/data/public_suffix_list.dat
test/test_main.py
test/test_nicclient.py
test/test_parser.py
test/test_query.py